[{"created_at": "Thu Jun 25 20:34:57 +0000 2020", "id": 1276252562870562817, "id_str": "1276252562870562817", "text": "A Form 8-K [Press/News Current Report] filing has been made with the SEC:  $DPL DAYTON POWER &amp; LIGHT CO  DPL INC  https://t.co/QPzYvpBBX7", "source": "<a href=\"https://sec.report\" rel=\"nofollow\">Edgar Filings</a>", "truncated": false, "in_reply_to_status_id": null, "in_reply_to_status_id_str": null, "in_reply_to_user_id": null, "in_reply_to_user_id_str": null, "in_reply_to_screen_name": null, "user": {"id": 1068561714055012352, "id_str": "1068561714055012352", "name": "SEC.report", "screen_name": "EdgarInsider", "location": null, "url": "https://sec.report/", "description": "SEC filing alerts #SEC #InsiderTrading #Stocks #StockMarket #StockMarketNews #Edgar", "translator_type": "none", "protected": false, "verified": false, "followers_count": 486, "friends_count": 29, "listed_count": 8, "favourites_count": 388, "statuses_count": 8843, "created_at": "Fri Nov 30 17:45:40 +0000 2018", "utc_offset": null, "time_zone": null, "geo_enabled": false, "lang": null, "contributors_enabled": false, "is_translator": false, "profile_background_color": "F5F8FA", "profile_background_image_url": "", "profile_background_image_url_https": "", "profile_background_tile": false, "profile_link_color": "1DA1F2", "profile_sidebar_border_color": "C0DEED", "profile_sidebar_fill_color": "DDEEF6", "profile_text_color": "333333", "profile_use_background_image": true, "profile_image_url": "http://pbs.twimg.com/profile_images/1268972521941946368/GnspOt5e_normal.jpg", "profile_image_url_https": "https://pbs.twimg.com/profile_images/1268972521941946368/GnspOt5e_normal.jpg", "default_profile": true, "default_profile_image": false, "following": null, "follow_request_sent": null, "notifications": null}, "geo": null, "coordinates": null, "place": null, "contributors": null, "is_quote_status": false, "quote_count": 0, "reply_count": 0, "retweet_count": 0, "favorite_count": 0, "entities": {"hashtags": [], "urls": [{"url": "https://t.co/QPzYvpBBX7", "expanded_url": "https://sec.report/Document/0000787250-20-000035/", "display_url": "sec.report/Document/00007\u2026", "unwound": {"url": "https://sec.report/Document/0000787250-20-000035/", "status": 200, "title": "Dayton Power & Light Co 2020 Current Report 8-K", "description": "Dayton Power & Light Co Form 8-K"}, "indices": [118, 141]}], "user_mentions": [], "symbols": [{"text": "DPL", "indices": [75, 79]}]}, "favorited": false, "retweeted": false, "possibly_sensitive": false, "filter_level": "low", "lang": "en", "matching_rules": [{"tag": null}]}, {"created_at": "Sat Jun 20 00:24:56 +0000 2020", "id": 1274136112060121090, "id_str": "1274136112060121090", "text": "RT @AJBlackston: https://t.co/FIrrWvJPsu    DPL INC (0000787250) (Filer)       https://t.co/FIrrWvJPsu #TheLegalLowdown #Law #Regulations #\u2026", "source": "<a href=\"https://github.com/snowlew\" rel=\"nofollow\">Alpha-sun</a>", "truncated": false, "in_reply_to_status_id": null, "in_reply_to_status_id_str": null, "in_reply_to_user_id": null, "in_reply_to_user_id_str": null, "in_reply_to_screen_name": null, "user": {"id": 1082540114973245440, "id_str": "1082540114973245440", "name": "Bot CoronaVirus", "screen_name": "Bot_Corona_V", "location": "Brazil", "url": "https://github.com/SnowLew/Bot-CoronaVirus-Twitter", "description": "Apenas um bot que retweeta assuntos com rela\u00e7\u00e3o ao COVID-19.", "translator_type": "none", "derived": {"locations": [{"country": "Brazil", "country_code": "BR", "full_name": "Brazil", "geo": {"coordinates": [-55.0, -10.0], "type": "point"}}]}, "protected": false, "verified": false, "followers_count": 2184, "friends_count": 8, "listed_count": 12, "favourites_count": 12, "statuses_count": 228616, "created_at": "Tue Jan 08 07:30:50 +0000 2019", "utc_offset": null, "time_zone": null, "geo_enabled": false, "lang": null, "contributors_enabled": false, "is_translator": false, "profile_background_color": "F5F8FA", "profile_background_image_url": "", "profile_background_image_url_https": "", "profile_background_tile": false, "profile_link_color": "1DA1F2", "profile_sidebar_border_color": "C0DEED", "profile_sidebar_fill_color": "DDEEF6", "profile_text_color": "333333", "profile_use_background_image": true, "profile_image_url": "http://pbs.twimg.com/profile_images/1240134932699197441/es6-ohC8_normal.jpg", "profile_image_url_https": "https://pbs.twimg.com/profile_images/1240134932699197441/es6-ohC8_normal.jpg", "profile_banner_url": "https://pbs.twimg.com/profile_banners/1082540114973245440/1584506182", "default_profile": true, "default_profile_image": false, "following": null, "follow_request_sent": null, "notifications": null}, "geo": null, "coordinates": null, "place": null, "contributors": null, "retweeted_status": {"created_at": "Sat Jun 20 00:24:48 +0000 2020", "id": 1274136081579962369, "id_str": "1274136081579962369", "text": "https://t.co/FIrrWvJPsu    DPL INC (0000787250) (Filer)       https://t.co/FIrrWvJPsu #TheLegalLowdown #Law\u2026 https://t.co/qhM3It19k8", "source": "<a href=\"http://www.powerapps.com\" rel=\"nofollow\">Microsoft Power Platform</a>", "truncated": true, "in_reply_to_status_id": null, "in_reply_to_status_id_str": null, "in_reply_to_user_id": null, "in_reply_to_user_id_str": null, "in_reply_to_screen_name": null, "user": {"id": 344075523, "id_str": "344075523", "name": "AJ Blackston - Financial ERP Solution Consultant", "screen_name": "AJBlackston", "location": "Washington, DC", "url": "https://www.linkedin.com/in/ajblackston", "description": "AJ Blackston & Associates - a boutique Management Consulting firm based in  Washington, DC. ~Giving our clients what they want most . . . #SOLUTIONS! #LITFB", "translator_type": "none", "protected": false, "verified": false, "followers_count": 1736, "friends_count": 4153, "listed_count": 108, "favourites_count": 185, "statuses_count": 223258, "created_at": "Thu Jul 28 14:21:09 +0000 2011", "utc_offset": null, "time_zone": null, "geo_enabled": false, "lang": null, "contributors_enabled": false, "is_translator": false, "profile_background_color": "0F0C33", "profile_background_image_url": "http://abs.twimg.com/images/themes/theme1/bg.png", "profile_background_image_url_https": "https://abs.twimg.com/images/themes/theme1/bg.png", "profile_background_tile": false, "profile_link_color": "1058E8", "profile_sidebar_border_color": "08054D", "profile_sidebar_fill_color": "E3E2DE", "profile_text_color": "1E2375", "profile_use_background_image": false, "profile_image_url": "http://pbs.twimg.com/profile_images/459844339670056960/PP_6P7R-_normal.jpeg", "profile_image_url_https": "https://pbs.twimg.com/profile_images/459844339670056960/PP_6P7R-_normal.jpeg", "profile_banner_url": "https://pbs.twimg.com/profile_banners/344075523/1496188213", "default_profile": false, "default_profile_image": false, "following": null, "follow_request_sent": null, "notifications": null}, "geo": null, "coordinates": null, "place": null, "contributors": null, "is_quote_status": false, "extended_tweet": {"full_text": "https://t.co/FIrrWvJPsu    DPL INC (0000787250) (Filer)       https://t.co/FIrrWvJPsu #TheLegalLowdown #Law #Regulations #Compliance #COVID19 #Coronavirus #AI #Cybersecurity #Technology #Jury #Court #Lawyer #Lawfirm #Justice #Legal #Case #Attorney #IP #Litigation #Tort", "display_text_range": [0, 269], "entities": {"hashtags": [{"text": "TheLegalLowdown", "indices": [86, 102]}, {"text": "Law", "indices": [103, 107]}, {"text": "Regulations", "indices": [108, 120]}, {"text": "Compliance", "indices": [121, 132]}, {"text": "COVID19", "indices": [133, 141]}, {"text": "Coronavirus", "indices": [142, 154]}, {"text": "AI", "indices": [155, 158]}, {"text": "Cybersecurity", "indices": [159, 173]}, {"text": "Technology", "indices": [174, 185]}, {"text": "Jury", "indices": [186, 191]}, {"text": "Court", "indices": [192, 198]}, {"text": "Lawyer", "indices": [199, 206]}, {"text": "Lawfirm", "indices": [207, 215]}, {"text": "Justice", "indices": [216, 224]}, {"text": "Legal", "indices": [225, 231]}, {"text": "Case", "indices": [232, 237]}, {"text": "Attorney", "indices": [238, 247]}, {"text": "IP", "indices": [248, 251]}, {"text": "Litigation", "indices": [252, 263]}, {"text": "Tort", "indices": [264, 269]}], "urls": [{"url": "https://t.co/FIrrWvJPsu", "expanded_url": "https://www.sec.gov/Archives/edgar/data/787250/000095010320012087/0000950103-20-012087-index.htm", "display_url": "sec.gov/Archives/edgar\u2026", "unwound": {"url": "https://www.sec.gov/Archives/edgar/data/787250/000095010320012087/0000950103-20-012087-index.htm", "status": 200, "title": "EDGAR Filing Documents for 0000950103-20-012087", "description": "SEC Accession No. 0000950103-20-012087 Item 1.01: Entry into a Material Definitive Agreement Item 2.03: Creation of a Direct Financial Obligation or an Obligation under an Off-Balance Sheet Arrangement of a Registrant Item 9.01: Financial Statements and Exhibits DPL INC (Filer) CIK: 0000787250 (see all company filings) IRS No.: 311163136 | State of Incorp.: OH | Fiscal Year End: 1231 Type: 8-K | Act: 34 | File No.: 001-09052 | Film No.: 20976071 SIC: 4931 Electric & Other Services Combined Office of"}, "indices": [0, 23]}, {"url": "https://t.co/FIrrWvJPsu", "expanded_url": "https://www.sec.gov/Archives/edgar/data/787250/000095010320012087/0000950103-20-012087-index.htm", "display_url": "sec.gov/Archives/edgar\u2026", "unwound": {"url": "https://www.sec.gov/Archives/edgar/data/787250/000095010320012087/0000950103-20-012087-index.htm", "status": 200, "title": "EDGAR Filing Documents for 0000950103-20-012087", "description": "SEC Accession No. 0000950103-20-012087 Item 1.01: Entry into a Material Definitive Agreement Item 2.03: Creation of a Direct Financial Obligation or an Obligation under an Off-Balance Sheet Arrangement of a Registrant Item 9.01: Financial Statements and Exhibits DPL INC (Filer) CIK: 0000787250 (see all company filings) IRS No.: 311163136 | State of Incorp.: OH | Fiscal Year End: 1231 Type: 8-K | Act: 34 | File No.: 001-09052 | Film No.: 20976071 SIC: 4931 Electric & Other Services Combined Office of"}, "indices": [62, 85]}], "user_mentions": [], "symbols": []}}, "quote_count": 0, "reply_count": 0, "retweet_count": 1, "favorite_count": 0, "entities": {"hashtags": [{"text": "TheLegalLowdown", "indices": [86, 102]}, {"text": "Law", "indices": [103, 107]}], "urls": [{"url": "https://t.co/FIrrWvJPsu", "expanded_url": "https://www.sec.gov/Archives/edgar/data/787250/000095010320012087/0000950103-20-012087-index.htm", "display_url": "sec.gov/Archives/edgar\u2026", "unwound": {"url": "https://www.sec.gov/Archives/edgar/data/787250/000095010320012087/0000950103-20-012087-index.htm", "status": 200, "title": "EDGAR Filing Documents for 0000950103-20-012087", "description": "SEC Accession No. 0000950103-20-012087 Item 1.01: Entry into a Material Definitive Agreement Item 2.03: Creation of a Direct Financial Obligation or an Obligation under an Off-Balance Sheet Arrangement of a Registrant Item 9.01: Financial Statements and Exhibits DPL INC (Filer) CIK: 0000787250 (see all company filings) IRS No.: 311163136 | State of Incorp.: OH | Fiscal Year End: 1231 Type: 8-K | Act: 34 | File No.: 001-09052 | Film No.: 20976071 SIC: 4931 Electric & Other Services Combined Office of"}, "indices": [0, 23]}, {"url": "https://t.co/FIrrWvJPsu", "expanded_url": "https://www.sec.gov/Archives/edgar/data/787250/000095010320012087/0000950103-20-012087-index.htm", "display_url": "sec.gov/Archives/edgar\u2026", "unwound": {"url": "https://www.sec.gov/Archives/edgar/data/787250/000095010320012087/0000950103-20-012087-index.htm", "status": 200, "title": "EDGAR Filing Documents for 0000950103-20-012087", "description": "SEC Accession No. 0000950103-20-012087 Item 1.01: Entry into a Material Definitive Agreement Item 2.03: Creation of a Direct Financial Obligation or an Obligation under an Off-Balance Sheet Arrangement of a Registrant Item 9.01: Financial Statements and Exhibits DPL INC (Filer) CIK: 0000787250 (see all company filings) IRS No.: 311163136 | State of Incorp.: OH | Fiscal Year End: 1231 Type: 8-K | Act: 34 | File No.: 001-09052 | Film No.: 20976071 SIC: 4931 Electric & Other Services Combined Office of"}, "indices": [62, 85]}, {"url": "https://t.co/qhM3It19k8", "expanded_url": "https://twitter.com/i/web/status/1274136081579962369", "display_url": "twitter.com/i/web/status/1\u2026", "indices": [109, 132]}], "user_mentions": [], "symbols": []}, "favorited": false, "retweeted": false, "possibly_sensitive": false, "filter_level": "low", "lang": "pt"}, "is_quote_status": false, "quote_count": 0, "reply_count": 0, "retweet_count": 0, "favorite_count": 0, "entities": {"hashtags": [{"text": "TheLegalLowdown", "indices": [103, 119]}, {"text": "Law", "indices": [120, 124]}, {"text": "Regulations", "indices": [125, 137]}], "urls": [{"url": "https://t.co/FIrrWvJPsu", "expanded_url": "https://www.sec.gov/Archives/edgar/data/787250/000095010320012087/0000950103-20-012087-index.htm", "display_url": "sec.gov/Archives/edgar\u2026", "unwound": {"url": "https://www.sec.gov/Archives/edgar/data/787250/000095010320012087/0000950103-20-012087-index.htm", "status": 200, "title": "EDGAR Filing Documents for 0000950103-20-012087", "description": "SEC Accession No. 0000950103-20-012087 Item 1.01: Entry into a Material Definitive Agreement Item 2.03: Creation of a Direct Financial Obligation or an Obligation under an Off-Balance Sheet Arrangement of a Registrant Item 9.01: Financial Statements and Exhibits DPL INC (Filer) CIK: 0000787250 (see all company filings) IRS No.: 311163136 | State of Incorp.: OH | Fiscal Year End: 1231 Type: 8-K | Act: 34 | File No.: 001-09052 | Film No.: 20976071 SIC: 4931 Electric & Other Services Combined Office of"}, "indices": [17, 40]}, {"url": "https://t.co/FIrrWvJPsu", "expanded_url": "https://www.sec.gov/Archives/edgar/data/787250/000095010320012087/0000950103-20-012087-index.htm", "display_url": "sec.gov/Archives/edgar\u2026", "unwound": {"url": "https://www.sec.gov/Archives/edgar/data/787250/000095010320012087/0000950103-20-012087-index.htm", "status": 200, "title": "EDGAR Filing Documents for 0000950103-20-012087", "description": "SEC Accession No. 0000950103-20-012087 Item 1.01: Entry into a Material Definitive Agreement Item 2.03: Creation of a Direct Financial Obligation or an Obligation under an Off-Balance Sheet Arrangement of a Registrant Item 9.01: Financial Statements and Exhibits DPL INC (Filer) CIK: 0000787250 (see all company filings) IRS No.: 311163136 | State of Incorp.: OH | Fiscal Year End: 1231 Type: 8-K | Act: 34 | File No.: 001-09052 | Film No.: 20976071 SIC: 4931 Electric & Other Services Combined Office of"}, "indices": [79, 102]}], "user_mentions": [{"screen_name": "AJBlackston", "name": "AJ Blackston - Financial ERP Solution Consultant", "id": 344075523, "id_str": "344075523", "indices": [3, 15]}], "symbols": []}, "favorited": false, "retweeted": false, "possibly_sensitive": false, "filter_level": "low", "lang": "pt", "matching_rules": [{"tag": null}]}, {"created_at": "Sat Jun 20 00:24:56 +0000 2020", "id": 1274136112005615617, "id_str": "1274136112005615617", "text": "RT @AJBlackston: https://t.co/FIrrWvseAW    DPL INC (0000787250) (Filer)       https://t.co/FIrrWvseAW #TheLegalLowdown #Law #Regulations #\u2026", "source": "<a href=\"https://github.com/snowlew\" rel=\"nofollow\">Alpha-sun</a>", "truncated": false, "in_reply_to_status_id": null, "in_reply_to_status_id_str": null, "in_reply_to_user_id": null, "in_reply_to_user_id_str": null, "in_reply_to_screen_name": null, "user": {"id": 1082540114973245440, "id_str": "1082540114973245440", "name": "Bot CoronaVirus", "screen_name": "Bot_Corona_V", "location": "Brazil", "url": "https://github.com/SnowLew/Bot-CoronaVirus-Twitter", "description": "Apenas um bot que retweeta assuntos com rela\u00e7\u00e3o ao COVID-19.", "translator_type": "none", "derived": {"locations": [{"country": "Brazil", "country_code": "BR", "full_name": "Brazil", "geo": {"coordinates": [-55.0, -10.0], "type": "point"}}]}, "protected": false, "verified": false, "followers_count": 2184, "friends_count": 8, "listed_count": 12, "favourites_count": 12, "statuses_count": 228616, "created_at": "Tue Jan 08 07:30:50 +0000 2019", "utc_offset": null, "time_zone": null, "geo_enabled": false, "lang": null, "contributors_enabled": false, "is_translator": false, "profile_background_color": "F5F8FA", "profile_background_image_url": "", "profile_background_image_url_https": "", "profile_background_tile": false, "profile_link_color": "1DA1F2", "profile_sidebar_border_color": "C0DEED", "profile_sidebar_fill_color": "DDEEF6", "profile_text_color": "333333", "profile_use_background_image": true, "profile_image_url": "http://pbs.twimg.com/profile_images/1240134932699197441/es6-ohC8_normal.jpg", "profile_image_url_https": "https://pbs.twimg.com/profile_images/1240134932699197441/es6-ohC8_normal.jpg", "profile_banner_url": "https://pbs.twimg.com/profile_banners/1082540114973245440/1584506182", "default_profile": true, "default_profile_image": false, "following": null, "follow_request_sent": null, "notifications": null}, "geo": null, "coordinates": null, "place": null, "contributors": null, "retweeted_status": {"created_at": "Sat Jun 20 00:24:49 +0000 2020", "id": 1274136082746146818, "id_str": "1274136082746146818", "text": "https://t.co/FIrrWvseAW    DPL INC (0000787250) (Filer)       https://t.co/FIrrWvseAW #TheLegalLowdown #Law\u2026 https://t.co/JE0hfRWdkn", "source": "<a href=\"http://www.powerapps.com\" rel=\"nofollow\">Microsoft Power Platform</a>", "truncated": true, "in_reply_to_status_id": null, "in_reply_to_status_id_str": null, "in_reply_to_user_id": null, "in_reply_to_user_id_str": null, "in_reply_to_screen_name": null, "user": {"id": 344075523, "id_str": "344075523", "name": "AJ Blackston - Financial ERP Solution Consultant", "screen_name": "AJBlackston", "location": "Washington, DC", "url": "https://www.linkedin.com/in/ajblackston", "description": "AJ Blackston & Associates - a boutique Management Consulting firm based in  Washington, DC. ~Giving our clients what they want most . . . #SOLUTIONS! #LITFB", "translator_type": "none", "protected": false, "verified": false, "followers_count": 1736, "friends_count": 4153, "listed_count": 108, "favourites_count": 185, "statuses_count": 223258, "created_at": "Thu Jul 28 14:21:09 +0000 2011", "utc_offset": null, "time_zone": null, "geo_enabled": false, "lang": null, "contributors_enabled": false, "is_translator": false, "profile_background_color": "0F0C33", "profile_background_image_url": "http://abs.twimg.com/images/themes/theme1/bg.png", "profile_background_image_url_https": "https://abs.twimg.com/images/themes/theme1/bg.png", "profile_background_tile": false, "profile_link_color": "1058E8", "profile_sidebar_border_color": "08054D", "profile_sidebar_fill_color": "E3E2DE", "profile_text_color": "1E2375", "profile_use_background_image": false, "profile_image_url": "http://pbs.twimg.com/profile_images/459844339670056960/PP_6P7R-_normal.jpeg", "profile_image_url_https": "https://pbs.twimg.com/profile_images/459844339670056960/PP_6P7R-_normal.jpeg", "profile_banner_url": "https://pbs.twimg.com/profile_banners/344075523/1496188213", "default_profile": false, "default_profile_image": false, "following": null, "follow_request_sent": null, "notifications": null}, "geo": null, "coordinates": null, "place": null, "contributors": null, "is_quote_status": false, "extended_tweet": {"full_text": "https://t.co/FIrrWvseAW    DPL INC (0000787250) (Filer)       https://t.co/FIrrWvseAW #TheLegalLowdown #Law #Regulations #Compliance #COVID19 #Coronavirus #AI #Cybersecurity #Technology #Jury #Court #Lawyer #Lawfirm #Justice #Legal #Case #Attorney #IP #Litigation #Tort", "display_text_range": [0, 269], "entities": {"hashtags": [{"text": "TheLegalLowdown", "indices": [86, 102]}, {"text": "Law", "indices": [103, 107]}, {"text": "Regulations", "indices": [108, 120]}, {"text": "Compliance", "indices": [121, 132]}, {"text": "COVID19", "indices": [133, 141]}, {"text": "Coronavirus", "indices": [142, 154]}, {"text": "AI", "indices": [155, 158]}, {"text": "Cybersecurity", "indices": [159, 173]}, {"text": "Technology", "indices": [174, 185]}, {"text": "Jury", "indices": [186, 191]}, {"text": "Court", "indices": [192, 198]}, {"text": "Lawyer", "indices": [199, 206]}, {"text": "Lawfirm", "indices": [207, 215]}, {"text": "Justice", "indices": [216, 224]}, {"text": "Legal", "indices": [225, 231]}, {"text": "Case", "indices": [232, 237]}, {"text": "Attorney", "indices": [238, 247]}, {"text": "IP", "indices": [248, 251]}, {"text": "Litigation", "indices": [252, 263]}, {"text": "Tort", "indices": [264, 269]}], "urls": [{"url": "https://t.co/FIrrWvseAW", "expanded_url": "https://www.sec.gov/Archives/edgar/data/787250/000095010320012087/0000950103-20-012087-index.htm", "display_url": "sec.gov/Archives/edgar\u2026", "unwound": {"url": "https://www.sec.gov/Archives/edgar/data/787250/000095010320012087/0000950103-20-012087-index.htm", "status": 200, "title": "EDGAR Filing Documents for 0000950103-20-012087", "description": "SEC Accession No. 0000950103-20-012087 Item 1.01: Entry into a Material Definitive Agreement Item 2.03: Creation of a Direct Financial Obligation or an Obligation under an Off-Balance Sheet Arrangement of a Registrant Item 9.01: Financial Statements and Exhibits DPL INC (Filer) CIK: 0000787250 (see all company filings) IRS No.: 311163136 | State of Incorp.: OH | Fiscal Year End: 1231 Type: 8-K | Act: 34 | File No.: 001-09052 | Film No.: 20976071 SIC: 4931 Electric & Other Services Combined Office of"}, "indices": [0, 23]}, {"url": "https://t.co/FIrrWvseAW", "expanded_url": "https://www.sec.gov/Archives/edgar/data/787250/000095010320012087/0000950103-20-012087-index.htm", "display_url": "sec.gov/Archives/edgar\u2026", "unwound": {"url": "https://www.sec.gov/Archives/edgar/data/787250/000095010320012087/0000950103-20-012087-index.htm", "status": 200, "title": "EDGAR Filing Documents for 0000950103-20-012087", "description": "SEC Accession No. 0000950103-20-012087 Item 1.01: Entry into a Material Definitive Agreement Item 2.03: Creation of a Direct Financial Obligation or an Obligation under an Off-Balance Sheet Arrangement of a Registrant Item 9.01: Financial Statements and Exhibits DPL INC (Filer) CIK: 0000787250 (see all company filings) IRS No.: 311163136 | State of Incorp.: OH | Fiscal Year End: 1231 Type: 8-K | Act: 34 | File No.: 001-09052 | Film No.: 20976071 SIC: 4931 Electric & Other Services Combined Office of"}, "indices": [62, 85]}], "user_mentions": [], "symbols": []}}, "quote_count": 0, "reply_count": 0, "retweet_count": 1, "favorite_count": 0, "entities": {"hashtags": [{"text": "TheLegalLowdown", "indices": [86, 102]}, {"text": "Law", "indices": [103, 107]}], "urls": [{"url": "https://t.co/FIrrWvseAW", "expanded_url": "https://www.sec.gov/Archives/edgar/data/787250/000095010320012087/0000950103-20-012087-index.htm", "display_url": "sec.gov/Archives/edgar\u2026", "unwound": {"url": "https://www.sec.gov/Archives/edgar/data/787250/000095010320012087/0000950103-20-012087-index.htm", "status": 200, "title": "EDGAR Filing Documents for 0000950103-20-012087", "description": "SEC Accession No. 0000950103-20-012087 Item 1.01: Entry into a Material Definitive Agreement Item 2.03: Creation of a Direct Financial Obligation or an Obligation under an Off-Balance Sheet Arrangement of a Registrant Item 9.01: Financial Statements and Exhibits DPL INC (Filer) CIK: 0000787250 (see all company filings) IRS No.: 311163136 | State of Incorp.: OH | Fiscal Year End: 1231 Type: 8-K | Act: 34 | File No.: 001-09052 | Film No.: 20976071 SIC: 4931 Electric & Other Services Combined Office of"}, "indices": [0, 23]}, {"url": "https://t.co/FIrrWvseAW", "expanded_url": "https://www.sec.gov/Archives/edgar/data/787250/000095010320012087/0000950103-20-012087-index.htm", "display_url": "sec.gov/Archives/edgar\u2026", "unwound": {"url": "https://www.sec.gov/Archives/edgar/data/787250/000095010320012087/0000950103-20-012087-index.htm", "status": 200, "title": "EDGAR Filing Documents for 0000950103-20-012087", "description": "SEC Accession No. 0000950103-20-012087 Item 1.01: Entry into a Material Definitive Agreement Item 2.03: Creation of a Direct Financial Obligation or an Obligation under an Off-Balance Sheet Arrangement of a Registrant Item 9.01: Financial Statements and Exhibits DPL INC (Filer) CIK: 0000787250 (see all company filings) IRS No.: 311163136 | State of Incorp.: OH | Fiscal Year End: 1231 Type: 8-K | Act: 34 | File No.: 001-09052 | Film No.: 20976071 SIC: 4931 Electric & Other Services Combined Office of"}, "indices": [62, 85]}, {"url": "https://t.co/JE0hfRWdkn", "expanded_url": "https://twitter.com/i/web/status/1274136082746146818", "display_url": "twitter.com/i/web/status/1\u2026", "indices": [109, 132]}], "user_mentions": [], "symbols": []}, "favorited": false, "retweeted": false, "possibly_sensitive": false, "filter_level": "low", "lang": "pt"}, "is_quote_status": false, "quote_count": 0, "reply_count": 0, "retweet_count": 0, "favorite_count": 0, "entities": {"hashtags": [{"text": "TheLegalLowdown", "indices": [103, 119]}, {"text": "Law", "indices": [120, 124]}, {"text": "Regulations", "indices": [125, 137]}], "urls": [{"url": "https://t.co/FIrrWvseAW", "expanded_url": "https://www.sec.gov/Archives/edgar/data/787250/000095010320012087/0000950103-20-012087-index.htm", "display_url": "sec.gov/Archives/edgar\u2026", "unwound": {"url": "https://www.sec.gov/Archives/edgar/data/787250/000095010320012087/0000950103-20-012087-index.htm", "status": 200, "title": "EDGAR Filing Documents for 0000950103-20-012087", "description": "SEC Accession No. 0000950103-20-012087 Item 1.01: Entry into a Material Definitive Agreement Item 2.03: Creation of a Direct Financial Obligation or an Obligation under an Off-Balance Sheet Arrangement of a Registrant Item 9.01: Financial Statements and Exhibits DPL INC (Filer) CIK: 0000787250 (see all company filings) IRS No.: 311163136 | State of Incorp.: OH | Fiscal Year End: 1231 Type: 8-K | Act: 34 | File No.: 001-09052 | Film No.: 20976071 SIC: 4931 Electric & Other Services Combined Office of"}, "indices": [17, 40]}, {"url": "https://t.co/FIrrWvseAW", "expanded_url": "https://www.sec.gov/Archives/edgar/data/787250/000095010320012087/0000950103-20-012087-index.htm", "display_url": "sec.gov/Archives/edgar\u2026", "unwound": {"url": "https://www.sec.gov/Archives/edgar/data/787250/000095010320012087/0000950103-20-012087-index.htm", "status": 200, "title": "EDGAR Filing Documents for 0000950103-20-012087", "description": "SEC Accession No. 0000950103-20-012087 Item 1.01: Entry into a Material Definitive Agreement Item 2.03: Creation of a Direct Financial Obligation or an Obligation under an Off-Balance Sheet Arrangement of a Registrant Item 9.01: Financial Statements and Exhibits DPL INC (Filer) CIK: 0000787250 (see all company filings) IRS No.: 311163136 | State of Incorp.: OH | Fiscal Year End: 1231 Type: 8-K | Act: 34 | File No.: 001-09052 | Film No.: 20976071 SIC: 4931 Electric & Other Services Combined Office of"}, "indices": [79, 102]}], "user_mentions": [{"screen_name": "AJBlackston", "name": "AJ Blackston - Financial ERP Solution Consultant", "id": 344075523, "id_str": "344075523", "indices": [3, 15]}], "symbols": []}, "favorited": false, "retweeted": false, "possibly_sensitive": false, "filter_level": "low", "lang": "pt", "matching_rules": [{"tag": null}]}, {"created_at": "Sat Jun 20 00:24:49 +0000 2020", "id": 1274136082746146818, "id_str": "1274136082746146818", "text": "https://t.co/FIrrWvseAW    DPL INC (0000787250) (Filer)       https://t.co/FIrrWvseAW #TheLegalLowdown #Law\u2026 https://t.co/JE0hfRWdkn", "source": "<a href=\"http://www.powerapps.com\" rel=\"nofollow\">Microsoft Power Platform</a>", "truncated": true, "in_reply_to_status_id": null, "in_reply_to_status_id_str": null, "in_reply_to_user_id": null, "in_reply_to_user_id_str": null, "in_reply_to_screen_name": null, "user": {"id": 344075523, "id_str": "344075523", "name": "AJ Blackston - Financial ERP Solution Consultant", "screen_name": "AJBlackston", "location": "Washington, DC", "url": "https://www.linkedin.com/in/ajblackston", "description": "AJ Blackston & Associates - a boutique Management Consulting firm based in  Washington, DC. ~Giving our clients what they want most . . . #SOLUTIONS! #LITFB", "translator_type": "none", "derived": {"locations": [{"country": "United States", "country_code": "US", "region": "Washington, D.C.", "full_name": "Washington, D.C., United States", "geo": {"coordinates": [-77.00025, 38.91706], "type": "point"}}]}, "protected": false, "verified": false, "followers_count": 1736, "friends_count": 4153, "listed_count": 108, "favourites_count": 185, "statuses_count": 223258, "created_at": "Thu Jul 28 14:21:09 +0000 2011", "utc_offset": null, "time_zone": null, "geo_enabled": false, "lang": null, "contributors_enabled": false, "is_translator": false, "profile_background_color": "0F0C33", "profile_background_image_url": "http://abs.twimg.com/images/themes/theme1/bg.png", "profile_background_image_url_https": "https://abs.twimg.com/images/themes/theme1/bg.png", "profile_background_tile": false, "profile_link_color": "1058E8", "profile_sidebar_border_color": "08054D", "profile_sidebar_fill_color": "E3E2DE", "profile_text_color": "1E2375", "profile_use_background_image": false, "profile_image_url": "http://pbs.twimg.com/profile_images/459844339670056960/PP_6P7R-_normal.jpeg", "profile_image_url_https": "https://pbs.twimg.com/profile_images/459844339670056960/PP_6P7R-_normal.jpeg", "profile_banner_url": "https://pbs.twimg.com/profile_banners/344075523/1496188213", "default_profile": false, "default_profile_image": false, "following": null, "follow_request_sent": null, "notifications": null}, "geo": null, "coordinates": null, "place": null, "contributors": null, "is_quote_status": false, "extended_tweet": {"full_text": "https://t.co/FIrrWvseAW    DPL INC (0000787250) (Filer)       https://t.co/FIrrWvseAW #TheLegalLowdown #Law #Regulations #Compliance #COVID19 #Coronavirus #AI #Cybersecurity #Technology #Jury #Court #Lawyer #Lawfirm #Justice #Legal #Case #Attorney #IP #Litigation #Tort", "display_text_range": [0, 269], "entities": {"hashtags": [{"text": "TheLegalLowdown", "indices": [86, 102]}, {"text": "Law", "indices": [103, 107]}, {"text": "Regulations", "indices": [108, 120]}, {"text": "Compliance", "indices": [121, 132]}, {"text": "COVID19", "indices": [133, 141]}, {"text": "Coronavirus", "indices": [142, 154]}, {"text": "AI", "indices": [155, 158]}, {"text": "Cybersecurity", "indices": [159, 173]}, {"text": "Technology", "indices": [174, 185]}, {"text": "Jury", "indices": [186, 191]}, {"text": "Court", "indices": [192, 198]}, {"text": "Lawyer", "indices": [199, 206]}, {"text": "Lawfirm", "indices": [207, 215]}, {"text": "Justice", "indices": [216, 224]}, {"text": "Legal", "indices": [225, 231]}, {"text": "Case", "indices": [232, 237]}, {"text": "Attorney", "indices": [238, 247]}, {"text": "IP", "indices": [248, 251]}, {"text": "Litigation", "indices": [252, 263]}, {"text": "Tort", "indices": [264, 269]}], "urls": [{"url": "https://t.co/FIrrWvseAW", "expanded_url": "https://www.sec.gov/Archives/edgar/data/787250/000095010320012087/0000950103-20-012087-index.htm", "display_url": "sec.gov/Archives/edgar\u2026", "unwound": {"url": "https://www.sec.gov/Archives/edgar/data/787250/000095010320012087/0000950103-20-012087-index.htm", "status": 200, "title": "EDGAR Filing Documents for 0000950103-20-012087", "description": "SEC Accession No. 0000950103-20-012087 Item 1.01: Entry into a Material Definitive Agreement Item 2.03: Creation of a Direct Financial Obligation or an Obligation under an Off-Balance Sheet Arrangement of a Registrant Item 9.01: Financial Statements and Exhibits DPL INC (Filer) CIK: 0000787250 (see all company filings) IRS No.: 311163136 | State of Incorp.: OH | Fiscal Year End: 1231 Type: 8-K | Act: 34 | File No.: 001-09052 | Film No.: 20976071 SIC: 4931 Electric & Other Services Combined Office of"}, "indices": [0, 23]}, {"url": "https://t.co/FIrrWvseAW", "expanded_url": "https://www.sec.gov/Archives/edgar/data/787250/000095010320012087/0000950103-20-012087-index.htm", "display_url": "sec.gov/Archives/edgar\u2026", "unwound": {"url": "https://www.sec.gov/Archives/edgar/data/787250/000095010320012087/0000950103-20-012087-index.htm", "status": 200, "title": "EDGAR Filing Documents for 0000950103-20-012087", "description": "SEC Accession No. 0000950103-20-012087 Item 1.01: Entry into a Material Definitive Agreement Item 2.03: Creation of a Direct Financial Obligation or an Obligation under an Off-Balance Sheet Arrangement of a Registrant Item 9.01: Financial Statements and Exhibits DPL INC (Filer) CIK: 0000787250 (see all company filings) IRS No.: 311163136 | State of Incorp.: OH | Fiscal Year End: 1231 Type: 8-K | Act: 34 | File No.: 001-09052 | Film No.: 20976071 SIC: 4931 Electric & Other Services Combined Office of"}, "indices": [62, 85]}], "user_mentions": [], "symbols": []}}, "quote_count": 0, "reply_count": 0, "retweet_count": 1, "favorite_count": 0, "entities": {"hashtags": [{"text": "TheLegalLowdown", "indices": [86, 102]}, {"text": "Law", "indices": [103, 107]}], "urls": [{"url": "https://t.co/FIrrWvseAW", "expanded_url": "https://www.sec.gov/Archives/edgar/data/787250/000095010320012087/0000950103-20-012087-index.htm", "display_url": "sec.gov/Archives/edgar\u2026", "unwound": {"url": "https://www.sec.gov/Archives/edgar/data/787250/000095010320012087/0000950103-20-012087-index.htm", "status": 200, "title": "EDGAR Filing Documents for 0000950103-20-012087", "description": "SEC Accession No. 0000950103-20-012087 Item 1.01: Entry into a Material Definitive Agreement Item 2.03: Creation of a Direct Financial Obligation or an Obligation under an Off-Balance Sheet Arrangement of a Registrant Item 9.01: Financial Statements and Exhibits DPL INC (Filer) CIK: 0000787250 (see all company filings) IRS No.: 311163136 | State of Incorp.: OH | Fiscal Year End: 1231 Type: 8-K | Act: 34 | File No.: 001-09052 | Film No.: 20976071 SIC: 4931 Electric & Other Services Combined Office of"}, "indices": [0, 23]}, {"url": "https://t.co/FIrrWvseAW", "expanded_url": "https://www.sec.gov/Archives/edgar/data/787250/000095010320012087/0000950103-20-012087-index.htm", "display_url": "sec.gov/Archives/edgar\u2026", "unwound": {"url": "https://www.sec.gov/Archives/edgar/data/787250/000095010320012087/0000950103-20-012087-index.htm", "status": 200, "title": "EDGAR Filing Documents for 0000950103-20-012087", "description": "SEC Accession No. 0000950103-20-012087 Item 1.01: Entry into a Material Definitive Agreement Item 2.03: Creation of a Direct Financial Obligation or an Obligation under an Off-Balance Sheet Arrangement of a Registrant Item 9.01: Financial Statements and Exhibits DPL INC (Filer) CIK: 0000787250 (see all company filings) IRS No.: 311163136 | State of Incorp.: OH | Fiscal Year End: 1231 Type: 8-K | Act: 34 | File No.: 001-09052 | Film No.: 20976071 SIC: 4931 Electric & Other Services Combined Office of"}, "indices": [62, 85]}, {"url": "https://t.co/JE0hfRWdkn", "expanded_url": "https://twitter.com/i/web/status/1274136082746146818", "display_url": "twitter.com/i/web/status/1\u2026", "indices": [109, 132]}], "user_mentions": [], "symbols": []}, "favorited": false, "retweeted": false, "possibly_sensitive": false, "filter_level": "low", "lang": "pt", "matching_rules": [{"tag": null}]}, {"created_at": "Sat Jun 20 00:24:48 +0000 2020", "id": 1274136081579962369, "id_str": "1274136081579962369", "text": "https://t.co/FIrrWvJPsu    DPL INC (0000787250) (Filer)       https://t.co/FIrrWvJPsu #TheLegalLowdown #Law\u2026 https://t.co/qhM3It19k8", "source": "<a href=\"http://www.powerapps.com\" rel=\"nofollow\">Microsoft Power Platform</a>", "truncated": true, "in_reply_to_status_id": null, "in_reply_to_status_id_str": null, "in_reply_to_user_id": null, "in_reply_to_user_id_str": null, "in_reply_to_screen_name": null, "user": {"id": 344075523, "id_str": "344075523", "name": "AJ Blackston - Financial ERP Solution Consultant", "screen_name": "AJBlackston", "location": "Washington, DC", "url": "https://www.linkedin.com/in/ajblackston", "description": "AJ Blackston & Associates - a boutique Management Consulting firm based in  Washington, DC. ~Giving our clients what they want most . . . #SOLUTIONS! #LITFB", "translator_type": "none", "derived": {"locations": [{"country": "United States", "country_code": "US", "region": "Washington, D.C.", "full_name": "Washington, D.C., United States", "geo": {"coordinates": [-77.00025, 38.91706], "type": "point"}}]}, "protected": false, "verified": false, "followers_count": 1736, "friends_count": 4153, "listed_count": 108, "favourites_count": 185, "statuses_count": 223258, "created_at": "Thu Jul 28 14:21:09 +0000 2011", "utc_offset": null, "time_zone": null, "geo_enabled": false, "lang": null, "contributors_enabled": false, "is_translator": false, "profile_background_color": "0F0C33", "profile_background_image_url": "http://abs.twimg.com/images/themes/theme1/bg.png", "profile_background_image_url_https": "https://abs.twimg.com/images/themes/theme1/bg.png", "profile_background_tile": false, "profile_link_color": "1058E8", "profile_sidebar_border_color": "08054D", "profile_sidebar_fill_color": "E3E2DE", "profile_text_color": "1E2375", "profile_use_background_image": false, "profile_image_url": "http://pbs.twimg.com/profile_images/459844339670056960/PP_6P7R-_normal.jpeg", "profile_image_url_https": "https://pbs.twimg.com/profile_images/459844339670056960/PP_6P7R-_normal.jpeg", "profile_banner_url": "https://pbs.twimg.com/profile_banners/344075523/1496188213", "default_profile": false, "default_profile_image": false, "following": null, "follow_request_sent": null, "notifications": null}, "geo": null, "coordinates": null, "place": null, "contributors": null, "is_quote_status": false, "extended_tweet": {"full_text": "https://t.co/FIrrWvJPsu    DPL INC (0000787250) (Filer)       https://t.co/FIrrWvJPsu #TheLegalLowdown #Law #Regulations #Compliance #COVID19 #Coronavirus #AI #Cybersecurity #Technology #Jury #Court #Lawyer #Lawfirm #Justice #Legal #Case #Attorney #IP #Litigation #Tort", "display_text_range": [0, 269], "entities": {"hashtags": [{"text": "TheLegalLowdown", "indices": [86, 102]}, {"text": "Law", "indices": [103, 107]}, {"text": "Regulations", "indices": [108, 120]}, {"text": "Compliance", "indices": [121, 132]}, {"text": "COVID19", "indices": [133, 141]}, {"text": "Coronavirus", "indices": [142, 154]}, {"text": "AI", "indices": [155, 158]}, {"text": "Cybersecurity", "indices": [159, 173]}, {"text": "Technology", "indices": [174, 185]}, {"text": "Jury", "indices": [186, 191]}, {"text": "Court", "indices": [192, 198]}, {"text": "Lawyer", "indices": [199, 206]}, {"text": "Lawfirm", "indices": [207, 215]}, {"text": "Justice", "indices": [216, 224]}, {"text": "Legal", "indices": [225, 231]}, {"text": "Case", "indices": [232, 237]}, {"text": "Attorney", "indices": [238, 247]}, {"text": "IP", "indices": [248, 251]}, {"text": "Litigation", "indices": [252, 263]}, {"text": "Tort", "indices": [264, 269]}], "urls": [{"url": "https://t.co/FIrrWvJPsu", "expanded_url": "https://www.sec.gov/Archives/edgar/data/787250/000095010320012087/0000950103-20-012087-index.htm", "display_url": "sec.gov/Archives/edgar\u2026", "unwound": {"url": "https://www.sec.gov/Archives/edgar/data/787250/000095010320012087/0000950103-20-012087-index.htm", "status": 200, "title": "EDGAR Filing Documents for 0000950103-20-012087", "description": "SEC Accession No. 0000950103-20-012087 Item 1.01: Entry into a Material Definitive Agreement Item 2.03: Creation of a Direct Financial Obligation or an Obligation under an Off-Balance Sheet Arrangement of a Registrant Item 9.01: Financial Statements and Exhibits DPL INC (Filer) CIK: 0000787250 (see all company filings) IRS No.: 311163136 | State of Incorp.: OH | Fiscal Year End: 1231 Type: 8-K | Act: 34 | File No.: 001-09052 | Film No.: 20976071 SIC: 4931 Electric & Other Services Combined Office of"}, "indices": [0, 23]}, {"url": "https://t.co/FIrrWvJPsu", "expanded_url": "https://www.sec.gov/Archives/edgar/data/787250/000095010320012087/0000950103-20-012087-index.htm", "display_url": "sec.gov/Archives/edgar\u2026", "unwound": {"url": "https://www.sec.gov/Archives/edgar/data/787250/000095010320012087/0000950103-20-012087-index.htm", "status": 200, "title": "EDGAR Filing Documents for 0000950103-20-012087", "description": "SEC Accession No. 0000950103-20-012087 Item 1.01: Entry into a Material Definitive Agreement Item 2.03: Creation of a Direct Financial Obligation or an Obligation under an Off-Balance Sheet Arrangement of a Registrant Item 9.01: Financial Statements and Exhibits DPL INC (Filer) CIK: 0000787250 (see all company filings) IRS No.: 311163136 | State of Incorp.: OH | Fiscal Year End: 1231 Type: 8-K | Act: 34 | File No.: 001-09052 | Film No.: 20976071 SIC: 4931 Electric & Other Services Combined Office of"}, "indices": [62, 85]}], "user_mentions": [], "symbols": []}}, "quote_count": 0, "reply_count": 0, "retweet_count": 1, "favorite_count": 0, "entities": {"hashtags": [{"text": "TheLegalLowdown", "indices": [86, 102]}, {"text": "Law", "indices": [103, 107]}], "urls": [{"url": "https://t.co/FIrrWvJPsu", "expanded_url": "https://www.sec.gov/Archives/edgar/data/787250/000095010320012087/0000950103-20-012087-index.htm", "display_url": "sec.gov/Archives/edgar\u2026", "unwound": {"url": "https://www.sec.gov/Archives/edgar/data/787250/000095010320012087/0000950103-20-012087-index.htm", "status": 200, "title": "EDGAR Filing Documents for 0000950103-20-012087", "description": "SEC Accession No. 0000950103-20-012087 Item 1.01: Entry into a Material Definitive Agreement Item 2.03: Creation of a Direct Financial Obligation or an Obligation under an Off-Balance Sheet Arrangement of a Registrant Item 9.01: Financial Statements and Exhibits DPL INC (Filer) CIK: 0000787250 (see all company filings) IRS No.: 311163136 | State of Incorp.: OH | Fiscal Year End: 1231 Type: 8-K | Act: 34 | File No.: 001-09052 | Film No.: 20976071 SIC: 4931 Electric & Other Services Combined Office of"}, "indices": [0, 23]}, {"url": "https://t.co/FIrrWvJPsu", "expanded_url": "https://www.sec.gov/Archives/edgar/data/787250/000095010320012087/0000950103-20-012087-index.htm", "display_url": "sec.gov/Archives/edgar\u2026", "unwound": {"url": "https://www.sec.gov/Archives/edgar/data/787250/000095010320012087/0000950103-20-012087-index.htm", "status": 200, "title": "EDGAR Filing Documents for 0000950103-20-012087", "description": "SEC Accession No. 0000950103-20-012087 Item 1.01: Entry into a Material Definitive Agreement Item 2.03: Creation of a Direct Financial Obligation or an Obligation under an Off-Balance Sheet Arrangement of a Registrant Item 9.01: Financial Statements and Exhibits DPL INC (Filer) CIK: 0000787250 (see all company filings) IRS No.: 311163136 | State of Incorp.: OH | Fiscal Year End: 1231 Type: 8-K | Act: 34 | File No.: 001-09052 | Film No.: 20976071 SIC: 4931 Electric & Other Services Combined Office of"}, "indices": [62, 85]}, {"url": "https://t.co/qhM3It19k8", "expanded_url": "https://twitter.com/i/web/status/1274136081579962369", "display_url": "twitter.com/i/web/status/1\u2026", "indices": [109, 132]}], "user_mentions": [], "symbols": []}, "favorited": false, "retweeted": false, "possibly_sensitive": false, "filter_level": "low", "lang": "pt", "matching_rules": [{"tag": null}]}, {"created_at": "Fri Jun 19 20:36:03 +0000 2020", "id": 1274078513180508160, "id_str": "1274078513180508160", "text": "Filing for 8-K [Press/News Current Report] has been made with the SEC:  $DPL DPL INC  https://t.co/jbZl9FR8Hf", "source": "<a href=\"https://sec.report\" rel=\"nofollow\">Edgar Filings</a>", "truncated": false, "in_reply_to_status_id": null, "in_reply_to_status_id_str": null, "in_reply_to_user_id": null, "in_reply_to_user_id_str": null, "in_reply_to_screen_name": null, "user": {"id": 1068561714055012352, "id_str": "1068561714055012352", "name": "SEC.report", "screen_name": "EdgarInsider", "location": null, "url": "https://sec.report/", "description": "SEC filing alerts #SEC #InsiderTrading #Stocks #StockMarket #StockMarketNews #Edgar", "translator_type": "none", "protected": false, "verified": false, "followers_count": 486, "friends_count": 29, "listed_count": 8, "favourites_count": 388, "statuses_count": 8843, "created_at": "Fri Nov 30 17:45:40 +0000 2018", "utc_offset": null, "time_zone": null, "geo_enabled": false, "lang": null, "contributors_enabled": false, "is_translator": false, "profile_background_color": "F5F8FA", "profile_background_image_url": "", "profile_background_image_url_https": "", "profile_background_tile": false, "profile_link_color": "1DA1F2", "profile_sidebar_border_color": "C0DEED", "profile_sidebar_fill_color": "DDEEF6", "profile_text_color": "333333", "profile_use_background_image": true, "profile_image_url": "http://pbs.twimg.com/profile_images/1268972521941946368/GnspOt5e_normal.jpg", "profile_image_url_https": "https://pbs.twimg.com/profile_images/1268972521941946368/GnspOt5e_normal.jpg", "default_profile": true, "default_profile_image": false, "following": null, "follow_request_sent": null, "notifications": null}, "geo": null, "coordinates": null, "place": null, "contributors": null, "is_quote_status": false, "quote_count": 0, "reply_count": 0, "retweet_count": 0, "favorite_count": 0, "entities": {"hashtags": [], "urls": [{"url": "https://t.co/jbZl9FR8Hf", "expanded_url": "https://sec.report/Document/0000950103-20-012087/", "display_url": "sec.report/Document/00009\u2026", "unwound": {"url": "https://sec.report/Document/0000950103-20-012087/", "status": 200, "title": "Dpl Inc 2020 Current Report 8-K", "description": "Dpl Inc Form 8-K"}, "indices": [86, 109]}], "user_mentions": [], "symbols": [{"text": "DPL", "indices": [72, 76]}]}, "favorited": false, "retweeted": false, "possibly_sensitive": false, "filter_level": "low", "lang": "en", "matching_rules": [{"tag": null}]}, {"created_at": "Wed Jun 17 20:00:00 +0000 2020", "id": 1273344666071695360, "id_str": "1273344666071695360", "text": "The parent organization of The Dayton Power and Light Co. is looking to raise $415 million in senior debt to pay of\u2026 https://t.co/zR16zKEHsT", "source": "<a href=\"https://trueanthem.com/\" rel=\"nofollow\">True Anthem</a>", "truncated": true, "in_reply_to_status_id": null, "in_reply_to_status_id_str": null, "in_reply_to_user_id": null, "in_reply_to_user_id_str": null, "in_reply_to_screen_name": null, "user": {"id": 29209295, "id_str": "29209295", "name": "Dayton Biz Journal", "screen_name": "DBJnews", "location": "Dayton OH USA", "url": "http://bizjournals.com/dayton", "description": "Dayton Region's Best Source for Local Business News", "translator_type": "none", "derived": {"locations": [{"country": "United States", "country_code": "US", "locality": "Dayton", "region": "Ohio", "sub_region": "Montgomery County", "full_name": "Dayton, Ohio, United States", "geo": {"coordinates": [-84.19161, 39.75895], "type": "point"}}]}, "protected": false, "verified": false, "followers_count": 11683, "friends_count": 712, "listed_count": 364, "favourites_count": 381, "statuses_count": 41593, "created_at": "Mon Apr 06 14:26:31 +0000 2009", "utc_offset": null, "time_zone": null, "geo_enabled": false, "lang": null, "contributors_enabled": false, "is_translator": false, "profile_background_color": "781020", "profile_background_image_url": "http://abs.twimg.com/images/themes/theme1/bg.png", "profile_background_image_url_https": "https://abs.twimg.com/images/themes/theme1/bg.png", "profile_background_tile": false, "profile_link_color": "781020", "profile_sidebar_border_color": "FFFFFF", "profile_sidebar_fill_color": "E3E3E3", "profile_text_color": "292929", "profile_use_background_image": true, "profile_image_url": "http://pbs.twimg.com/profile_images/431531496461963264/xJ-A6UQj_normal.png", "profile_image_url_https": "https://pbs.twimg.com/profile_images/431531496461963264/xJ-A6UQj_normal.png", "profile_banner_url": "https://pbs.twimg.com/profile_banners/29209295/1553014128", "default_profile": false, "default_profile_image": false, "following": null, "follow_request_sent": null, "notifications": null}, "geo": null, "coordinates": null, "place": null, "contributors": null, "is_quote_status": false, "extended_tweet": {"full_text": "The parent organization of The Dayton Power and Light Co. is looking to raise $415 million in senior debt to pay off the remainder of outstanding debt scheduled to come next year.\u200b https://t.co/5wZurko3AE", "display_text_range": [0, 204], "entities": {"hashtags": [], "urls": [{"url": "https://t.co/5wZurko3AE", "expanded_url": "https://www.bizjournals.com/dayton/news/2020/06/17/dpl-inc-looks-to-raise-415-million-in-debt-offer.html?ana=TRUEANTHEMTWT_DY&csrc=6398&taid=5eea76402939cf00014a622b&utm_campaign=trueAnthem%3A+Trending+Content&utm_medium=trueAnthem&utm_source=twitter", "display_url": "bizjournals.com/dayton/news/20\u2026", "unwound": {"url": "https://www.bizjournals.com/dayton/news/2020/06/17/dpl-inc-looks-to-raise-415-million-in-debt-offer.html?ana=TRUEANTHEMTWT_DY&csrc=6398&taid=5eea76402939cf00014a622b&utm_campaign=trueAnthem%3A+Trending+Content&utm_medium=trueAnthem&utm_source=twitter", "status": 200, "title": "DP&L parent looks to raise $415 million in debt", "description": "The parent organization of The Dayton Power and Light Co. is looking to raise $415 million in senior debt to pay off the remainder of outstanding debt scheduled to come next year."}, "indices": [181, 204]}], "user_mentions": [], "symbols": []}}, "quote_count": 0, "reply_count": 0, "retweet_count": 0, "favorite_count": 0, "entities": {"hashtags": [], "urls": [{"url": "https://t.co/zR16zKEHsT", "expanded_url": "https://twitter.com/i/web/status/1273344666071695360", "display_url": "twitter.com/i/web/status/1\u2026", "indices": [117, 140]}], "user_mentions": [], "symbols": []}, "favorited": false, "retweeted": false, "possibly_sensitive": false, "filter_level": "low", "lang": "en", "matching_rules": [{"tag": null}]}, {"created_at": "Wed Jun 17 15:52:16 +0000 2020", "id": 1273282322855591936, "id_str": "1273282322855591936", "text": "New Form 8-K [Current Report] entry filed by  $DPL DAYTON POWER &amp; LIGHT CO DPL INC https://t.co/hNXwDc9JpN", "source": "<a href=\"https://mobile.twitter.com\" rel=\"nofollow\">Twitter Web App</a>", "truncated": false, "in_reply_to_status_id": null, "in_reply_to_status_id_str": null, "in_reply_to_user_id": null, "in_reply_to_user_id_str": null, "in_reply_to_screen_name": null, "user": {"id": 1068561714055012352, "id_str": "1068561714055012352", "name": "SEC.report", "screen_name": "EdgarInsider", "location": null, "url": "https://sec.report/", "description": "SEC filing alerts #SEC #InsiderTrading #Stocks #StockMarket #StockMarketNews #Edgar", "translator_type": "none", "protected": false, "verified": false, "followers_count": 486, "friends_count": 29, "listed_count": 8, "favourites_count": 388, "statuses_count": 8843, "created_at": "Fri Nov 30 17:45:40 +0000 2018", "utc_offset": null, "time_zone": null, "geo_enabled": false, "lang": null, "contributors_enabled": false, "is_translator": false, "profile_background_color": "F5F8FA", "profile_background_image_url": "", "profile_background_image_url_https": "", "profile_background_tile": false, "profile_link_color": "1DA1F2", "profile_sidebar_border_color": "C0DEED", "profile_sidebar_fill_color": "DDEEF6", "profile_text_color": "333333", "profile_use_background_image": true, "profile_image_url": "http://pbs.twimg.com/profile_images/1268972521941946368/GnspOt5e_normal.jpg", "profile_image_url_https": "https://pbs.twimg.com/profile_images/1268972521941946368/GnspOt5e_normal.jpg", "default_profile": true, "default_profile_image": false, "following": null, "follow_request_sent": null, "notifications": null}, "geo": null, "coordinates": null, "place": null, "contributors": null, "is_quote_status": false, "quote_count": 0, "reply_count": 0, "retweet_count": 0, "favorite_count": 0, "entities": {"hashtags": [], "urls": [{"url": "https://t.co/hNXwDc9JpN", "expanded_url": "https://sec.report/Document/0000950103-20-011856/", "display_url": "sec.report/Document/00009\u2026", "unwound": {"url": "https://sec.report/Document/0000950103-20-011856/", "status": 200, "title": "Dayton Power & Light Co 2020 Current Report 8-K", "description": "Dayton Power & Light Co Form 8-K"}, "indices": [87, 110]}], "user_mentions": [], "symbols": [{"text": "DPL", "indices": [46, 50]}]}, "favorited": false, "retweeted": false, "possibly_sensitive": false, "filter_level": "low", "lang": "en", "matching_rules": [{"tag": null}]}]